s3backuptool/s3backuptool.py
s3backuptool-0.1.2.data/scripts/s3backuptool.py
s3backuptool-0.1.2.dist-info/DESCRIPTION.rst
s3backuptool-0.1.2.dist-info/METADATA
s3backuptool-0.1.2.dist-info/RECORD
s3backuptool-0.1.2.dist-info/WHEEL
s3backuptool-0.1.2.dist-info/metadata.json
s3backuptool-0.1.2.dist-info/top_level.txt
