Metadata-Version: 2.0
Name: s3backuptool
Version: 0.1.2
Summary: Command line backup tool which backups local files to Amazon S3. AES-256 client side encryption support is also available. Only regular files, symlinks and folders are backed up.
Home-page: https://bitbucket.org/alexandru_ionica/s3backuptool
Author: Alexandru Ionica
Author-email: alexandru@ionica.eu
License: GPLv2
Download-URL: https://bitbucket.org/alexandru_ionica/s3backuptool/get/0.1.2.tar.gz
Keywords: s3backup s3backuptool
Platform: UNKNOWN
Classifier: Development Status :: 3 - Alpha
Classifier: Intended Audience :: Developers
Classifier: Intended Audience :: System Administrators
Classifier: Topic :: System :: Archiving :: Backup
Classifier: License :: OSI Approved :: GNU General Public License v2 (GPLv2)
Classifier: Programming Language :: Python :: 2.7
Requires-Dist: boto
Requires-Dist: pycrypto
